[
  {
    "id": "nns-bundle-classic-nabu-cycles",
    "manifest": {
      "paks": [
        {
          "name": "1984 Cycle 1",
          "path": "cycle1"
        },
        {
          "name": "1984 Cycle 2",
          "path": "cycle2"
        },
        {
          "name": "1986 Cycle 3",
          "path": "cycle3"
        },
        {
          "path": "direct",
          "options": {
            "exploitloader": true
          },
          "name": "Cycle Direct"
        }
      ]
    },
    "author": "The NABU Network",
    "version": "1.0.3",
    "description": "The classic 1984 NABU Network experience.\nAND Cycle Direct: skip the menu! \n",
    "path": "nns-bundle-classic-nabu-cycles.napa",
    "name": "Classic NABU Network Cycles"
  },
  {
    "id": "nns-bundle-ishkurcpm",
    "manifest": {
      "programs": [
        {
          "name": "Ishkur CPM NFS",
          "path": "NFS_HYBRID_BOOT.nabu"
        },
        {
          "name": "Ishkur CPM NDSK",
          "path": "NDSK_HYBRID_BOOT.nabu"
        },
        {
          "name": "Ishkur CPM IDE",
          "path": "IDE_BOOT.nabu"
        }
      ],
      "storage": [
        {
          "options": {
            "updatetype": "copy"
          },
          "path": "NDSK_A.IMG"
        },
        {
          "options": {
            "updatetype": "copy"
          },
          "path": "NDSK_B.IMG"
        }
      ]
    },
    "features": {
      "NHACPv01": true
    },
    "author": "teragav17",
    "url": "https://github.com/tergav17/IshkurCPM",
    "version": "0.1.3",
    "description": "Ishkur is a flavor of CPM 2.2 made for the NABU from the ground up. System files are loaded via NHACP. \nThis is the 'hybrid' flavor, and supports real drives (C & D) as well as cloud disks (A,B,E,etc).\n",
    "path": "nns-bundle-ishkurcpm.napa",
    "name": "Ishkur CPM"
  },
  {
    "id": "nns-bundle-nabuca",
    "manifest": {
      "storage": [
        {
          "options": {
            "updatetype": "copy"
          },
          "path": "CCPM"
        },
        {
          "options": {
            "updatetype": "copy"
          },
          "path": "C.dsk"
        }
      ],
      "sources": [
        {
          "path": "https://cloud.nabu.ca/HomeBrew/titles/filesv2.txt",
          "options": {
            "retronetserver": true,
            "retronet": true
          },
          "name": "NABU.ca"
        }
      ]
    },
    "features": {
      "retronet": true
    },
    "author": "NABU.ca",
    "url": "https://www.nabu.ca",
    "version": "1.0.3",
    "description": "Support for the NABU.ca feed and files for Cloud CP/M\n",
    "path": "nns-bundle-nabuca.napa",
    "name": "NABU.ca"
  },
  {
    "id": "nns-bundle-nabunetworkcom",
    "manifest": {
      "sources": [
        {
          "name": "NabuNetwork.com",
          "path": "https://www.nabunetwork.com/NabuNetwork.xml"
        }
      ]
    },
    "author": "NabuNetwork.com",
    "url": "https://nabunetwork.com",
    "version": "1.0.4.6",
    "description": "Support for the NabuNetwork.com feed.\n",
    "path": "nns-bundle-nabunetworkcom.napa",
    "name": "NabuNetwork.com"
  },
  {
    "id": "nns-bundle-productiondave-nabugames",
    "manifest": {
      "programs": [
        {
          "name": "Invaders",
          "path": "invaders.nabu"
        },
        {
          "name": "Snake",
          "path": "snake.nabu"
        },
        {
          "name": "Tetris",
          "path": "tetris.nabu"
        }
      ]
    },
    "author": "Production Dave",
    "url": "https://github.com/linuxplayground/nabu-games",
    "version": "3.5.3",
    "description": "A collection of games for the Nabu (and Z80 Retro) by Production Dave.\n",
    "path": "nns-bundle-productiondave-nabugames.napa",
    "name": "Production Dave's Nabu Games"
  },
  {
    "id": "nns-nabu-launcher",
    "manifest": {
      "paks": [
        {
          "path": "launcher",
          "options": {
            "headlessmenu": true
          },
          "name": "NABU Launcher"
        }
      ]
    },
    "author": "Nick Daniels",
    "url": "https://github.com/GryBsh/NabuNetworkEmulator",
    "version": "1.0.1",
    "description": "Launch NABU programs from the comfort of your couch. No UI required!.\nNNS can be switched into headless mode with `-s or --noui`\n",
    "path": "nns-nabu-launcher.napa",
    "name": "NABU Launcher"
  }
]
